{
  "fetched_at": "2026-07-01",
  "fetched_at_utc": "2026-07-01T13:00:00+00:00",
  "home_location": "Ahrensbök / Lübeck (23623)",
  "route_description": "Getrennte Flüge: Europa → Bangkok (BKK), Phuket (HKT) → Europa (inkl. Bodenkosten ab Zuhause)",
  "passengers": 2,
  "preferred_airlines": ["SQ", "CX", "TG"],
  "search_mode": "separate",
  "legs": [
    {
      "type": "leg", "direction": "outbound", "from": "HAM", "to": "BKK",
      "date": "2027-01-20", "cabin": "PREMIUM_ECONOMY", "airline_filter": null,
      "airlines": [], "price_eur_total": 2188, "price_eur_per_person": 1094
    },
    {
      "type": "leg", "direction": "inbound", "from": "HKT", "to": "HAM",
      "date": "2027-02-17", "cabin": "PREMIUM_ECONOMY", "airline_filter": null,
      "airlines": [], "price_eur_total": 2139, "price_eur_per_person": 1069
    },
    {
      "type": "leg", "direction": "outbound", "from": "CPH", "to": "BKK",
      "date": "2027-01-20", "cabin": "PREMIUM_ECONOMY", "airline_filter": null,
      "airlines": [], "price_eur_total": 1431, "price_eur_per_person": 715
    },
    {
      "type": "leg", "direction": "inbound", "from": "HKT", "to": "CPH",
      "date": "2027-02-17", "cabin": "PREMIUM_ECONOMY", "airline_filter": null,
      "airlines": [], "price_eur_total": 1984, "price_eur_per_person": 992
    },
    {
      "type": "leg", "direction": "outbound", "from": "CPH", "to": "BKK",
      "date": "2027-01-20", "cabin": "ECONOMY", "airline_filter": "TG",
      "airlines": ["TG"], "price_eur_total": 1165, "price_eur_per_person": 582
    },
    {
      "type": "leg", "direction": "outbound", "from": "HAM", "to": "BKK",
      "date": "2027-01-20", "cabin": "ECONOMY", "airline_filter": "TG",
      "airlines": ["TG"], "price_eur_total": 1435, "price_eur_per_person": 718
    }
  ],
  "combinations": [
    {
      "type": "combination",
      "origin": "CPH",
      "origin_label": "Kopenhagen",
      "departure": "2027-01-20",
      "return": "2027-02-17",
      "cabin": "PREMIUM_ECONOMY",
      "outbound_airlines": [],
      "inbound_airlines": [],
      "outbound_price_eur": 1431,
      "inbound_price_eur": 1984,
      "ground_mode": "Bahn",
      "ground_hours": 6.0,
      "ground_cost_eur": 90,
      "overnight_needed": false,
      "price_eur_total": 3505,
      "price_eur_per_person": 1752.5,
      "route": "Zuhause → CPH → BKK  |  HKT → CPH → Zuhause"
    },
    {
      "type": "combination",
      "origin": "HAM",
      "origin_label": "Hamburg",
      "departure": "2027-01-20",
      "return": "2027-02-17",
      "cabin": "PREMIUM_ECONOMY",
      "outbound_airlines": [],
      "inbound_airlines": [],
      "outbound_price_eur": 2188,
      "inbound_price_eur": 2139,
      "ground_mode": "Auto/Bahn",
      "ground_hours": 1.0,
      "ground_cost_eur": 50,
      "overnight_needed": false,
      "price_eur_total": 4377,
      "price_eur_per_person": 2188.5,
      "route": "Zuhause → HAM → BKK  |  HKT → HAM → Zuhause"
    }
  ],
  "open_jaw": []
}